alethic_ism_core-1.0.45.dist-info/licenses/LICENSE.md
ismcore/__init__.py
ismcore/base/__init__.py
ismcore/base/base_thread_queue_manager.py
ismcore/compiler/__init__.py
ismcore/compiler/runnable.py
ismcore/compiler/secure_runnable.py
ismcore/embedding/__init__.py
ismcore/embedding/datasource.py
ismcore/embedding/embedding_utils.py
ismcore/embedding/semantic_distance.py
ismcore/embedding/syntactic_accuracy.py
ismcore/messaging/__init__.py
ismcore/messaging/base_message_consumer_processor.py
ismcore/messaging/base_message_provider.py
ismcore/messaging/base_message_route_model.py
ismcore/messaging/base_message_router.py
ismcore/messaging/errors.py
ismcore/messaging/nats_message_provider.py
ismcore/messaging/nats_message_route.py
ismcore/model/__init__.py
ismcore/model/base_model.py
ismcore/model/base_model_usage_and_limits.py
ismcore/model/filter.py
ismcore/model/processor_state.py
ismcore/processor/__init__.py
ismcore/processor/base_processor.py
ismcore/processor/base_processor_lm.py
ismcore/processor/base_processor_visual.py
ismcore/processor/monitored_processor_state.py
ismcore/processor/processor_full_join.py
ismcore/storage/__init__.py
ismcore/storage/consumer_route_storage.py
ismcore/storage/processor_state_storage.py
ismcore/storage/redis_storage.py
ismcore/utils/__init__.py
ismcore/utils/evaluate.py
ismcore/utils/general_utils.py
ismcore/utils/ism_logger.py
ismcore/utils/map_utils.py
ismcore/utils/old_state_utils.py
ismcore/utils/state_utils.py
ismcore/vault/__init__.py
ismcore/vault/vault_model.py
alethic_ism_core-1.0.45.dist-info/METADATA
alethic_ism_core-1.0.45.dist-info/WHEEL
alethic_ism_core-1.0.45.dist-info/top_level.txt
alethic_ism_core-1.0.45.dist-info/RECORD
