Metadata-Version: 2.4
Name: alethic-ism-core
Version: 1.0.45
Summary: Alethic Instruction-Based State Machine (Core Python SDK)
Author-email: Kasra Rasaee <krasaee@gmail.com>, Sankalpa Ghose <sankalpa@alethic.ai>
Project-URL: Homepage, https://github.com/quantumwake/alethic-ism-core
Classifier: Programming Language :: Python :: 3
Classifier: Operating System :: OS Independent
Requires-Python: >=3.10
License-File: LICENSE.md
Dynamic: license-file
